blogg/__init__.py
blogg/admin.py
blogg/feed.py
blogg/models.py
blogg/tests.py
blogg/urls.py
blogg/views.py
blogg/migrations/.DS_Store
blogg/migrations/0001_initial.py
blogg/migrations/0002_comment.py
blogg/migrations/__init__.py
django_blogg-0.2.dist-info/DESCRIPTION.rst
django_blogg-0.2.dist-info/METADATA
django_blogg-0.2.dist-info/metadata.json
django_blogg-0.2.dist-info/RECORD
django_blogg-0.2.dist-info/top_level.txt
django_blogg-0.2.dist-info/WHEEL
